gpt_researcher/__init__.py
gpt_researcher/actions/__init__.py
gpt_researcher/actions/agent_creator.py
gpt_researcher/actions/markdown_processing.py
gpt_researcher/actions/query_processing.py
gpt_researcher/actions/report_generation.py
gpt_researcher/actions/retriever.py
gpt_researcher/actions/utils.py
gpt_researcher/actions/web_scraping.py
gpt_researcher/agent.py
gpt_researcher/config/__init__.py
gpt_researcher/config/config.py
gpt_researcher/config/variables/__init__.py
gpt_researcher/config/variables/base.py
gpt_researcher/config/variables/default.py
gpt_researcher/config/variables/test_local.json
gpt_researcher/context/__init__.py
gpt_researcher/context/compression.py
gpt_researcher/context/retriever.py
gpt_researcher/document/__init__.py
gpt_researcher/document/azure_document_loader.py
gpt_researcher/document/document.py
gpt_researcher/document/langchain_document.py
gpt_researcher/document/online_document.py
gpt_researcher/llm_provider/__init__.py
gpt_researcher/llm_provider/generic/__init__.py
gpt_researcher/llm_provider/generic/base.py
gpt_researcher/mcp/README.md
gpt_researcher/mcp/__init__.py
gpt_researcher/mcp/client.py
gpt_researcher/mcp/research.py
gpt_researcher/mcp/streaming.py
gpt_researcher/mcp/tool_selector.py
gpt_researcher/memory/__init__.py
gpt_researcher/memory/embeddings.py
gpt_researcher/prompts.py
gpt_researcher/retrievers/__init__.py
gpt_researcher/retrievers/arxiv/__init__.py
gpt_researcher/retrievers/arxiv/arxiv.py
gpt_researcher/retrievers/bing/__init__.py
gpt_researcher/retrievers/bing/bing.py
gpt_researcher/retrievers/custom/__init__.py
gpt_researcher/retrievers/custom/custom.py
gpt_researcher/retrievers/duckduckgo/__init__.py
gpt_researcher/retrievers/duckduckgo/duckduckgo.py
gpt_researcher/retrievers/exa/__init__.py
gpt_researcher/retrievers/exa/exa.py
gpt_researcher/retrievers/google/__init__.py
gpt_researcher/retrievers/google/google.py
gpt_researcher/retrievers/hasdata/__init__.py
gpt_researcher/retrievers/hasdata/hasdata.py
gpt_researcher_tomorrow-0.2.1.dist-info/METADATA
gpt_researcher_tomorrow-0.2.1.dist-info/WHEEL
gpt_researcher_tomorrow-0.2.1.dist-info/licenses/LICENSE
gpt_researcher_tomorrow-0.2.1.dist-info/RECORD
